zyla_api_hub/__init__.py
zyla_api_hub/client.py
zyla_hub_api-1.0.dist-info/METADATA
zyla_hub_api-1.0.dist-info/WHEEL
zyla_hub_api-1.0.dist-info/top_level.txt
zyla_hub_api-1.0.dist-info/RECORD
