Metadata-Version: 2.1
Name: zyla-hub-api
Version: 1.0
Summary: Find, Connect and Manage APIs
Home-page: https://github.com/Zyla-Labs/pypi-api-hub
Author: Zyla-API-Hub
Author-email: hello@zylalabs.com
Keywords: Api Hub,APIs,Find, Connect and Manage APIs,APIs Management,APIs Connection,APIs Integration,APIs Automation,APIs Development
